pandas_log/__init__.py
pandas_log/aop_utils.py
pandas_log/pandas_execution_stats.py
pandas_log/pandas_log.py
pandas_log/patched_logs_functions.py
pandas_log/settings.py
pandas_log-0.1.7.dist-info/AUTHORS.rst
pandas_log-0.1.7.dist-info/LICENSE
pandas_log-0.1.7.dist-info/METADATA
pandas_log-0.1.7.dist-info/WHEEL
pandas_log-0.1.7.dist-info/top_level.txt
pandas_log-0.1.7.dist-info/RECORD
