Metadata-Version: 2.1
Name: pandas-log
Version: 0.1.7
Summary: pandas-log provides feedback about basic pandas operations. It provides simple wrapper functions for the most common functions, such as apply, map, query and more.
Home-page: https://github.com/eyaltrabelsi/pandas-log
Author: Eyal Trabelsi
Author-email: eyaltrabelsi@gmail.com
License: MIT license
Platform: UNKNOWN
Requires-Python: >=3.4
Requires-Dist: humanize (>=0.5.0)
Requires-Dist: pandas (>=0.25.1)
Requires-Dist: pandas-flavor (>=0.1.2)
